{
	"animations": [
		{
			"offsets": [
				0,
				0
			],
			"loop": false,
			"fps": 34,
			"anim": "idle",
			"indices": [],
			"name": "idle"
		},
		{
			"offsets": [
				0,
				0
			],
			"loop": false,
			"fps": 34,
			"anim": "singLEFT",
			"indices": [],
			"name": "left"
		},
		{
			"offsets": [
				0,
				0
			],
			"loop": false,
			"fps": 34,
			"anim": "singDOWN",
			"indices": [],
			"name": "down"
		},
		{
			"offsets": [
				0,
				0
			],
			"loop": false,
			"fps": 34,
			"anim": "singUP",
			"indices": [],
			"name": "up"
		},
		{
			"offsets": [
				0,
				0
			],
			"loop": false,
			"fps": 34,
			"anim": "singRIGHT",
			"indices": [],
			"name": "right"
		}
	],
	"no_antialiasing": true,
	"image": "characters/guest1332",
	"position": [
		-90,
		140
	],
	"healthicon": "guest1332",
	"flip_x": false,
	"healthbar_colors": [
		95,
		22,
		39
	],
	"camera_position": [
		-390,
		-50
	],
	"sing_duration": 5.99999999999999,
	"scale": 1.4
}